sanskrit_text/__init__.py
sanskrit_text/cli.py
sanskrit_text-0.2.3.dist-info/AUTHORS.rst
sanskrit_text-0.2.3.dist-info/LICENSE
sanskrit_text-0.2.3.dist-info/METADATA
sanskrit_text-0.2.3.dist-info/WHEEL
sanskrit_text-0.2.3.dist-info/entry_points.txt
sanskrit_text-0.2.3.dist-info/top_level.txt
sanskrit_text-0.2.3.dist-info/RECORD
